serializers/__init__.py
serializers/deserialization.py
serializers/serialization.py
serializers/serializer.py
serializers/constants/__init__.py
serializers/constants/json_serializer_constants.py
serializers/constants/object_constants.py
serializers/constants/xml_serializer_constants.py
serializers/parsers/__init__.py
serializers/parsers/parser_factory_method.py
serializers/parsers/parser_interface.py
serializers/parsers/json_parser/__init__.py
serializers/parsers/json_parser/parser.py
serializers/parsers/xml_parser/__init__.py
serializers/parsers/xml_parser/parser.py
fj_serializer-0.2.0.dist-info/METADATA
fj_serializer-0.2.0.dist-info/WHEEL
fj_serializer-0.2.0.dist-info/top_level.txt
fj_serializer-0.2.0.dist-info/RECORD
